[
  {
    "kana": "アメリカンファミリーせいめい",
    "en": [
      "American Family Life Assurance",
      "Aflac"
    ],
    "senseUid": "763e55fd-4348-4d66-8390-e31063dc55b6",
    "wordId": "5010443",
    "pt": "Traduza do inglês para o português considerando o sentido japonês. Kana: アメリカンファミリーせいめい, Gloss: ['American Family Life Assurance', 'Aflac']"
  },
  {
    "kana": "アメリカこくどあんぜんほしょうしょう",
    "en": [
      "Department of Homeland Security (US)",
      "DHS"
    ],
    "senseUid": "98f26f27-7478-4f62-90ef-670dd9f9925a",
    "wordId": "5010446",
    "pt": "Traduza do inglês para o português considerando o sentido japonês. Kana: アメリカこくどあんぜんほしょうしょう, Glossário: ['Departamento de Segurança Interna (EUA)', 'DHS']"
  },
  {
    "kana": "アメリカこうくううちゅうきょく",
    "en": [
      "National Aeronautics and Space Administration (USA)",
      "NASA"
    ],
    "senseUid": "14e189c8-dd12-4021-aac1-efaeda358a45",
    "wordId": "5010445",
    "pt": "Traduza do inglês para o português considerando o sentido japonês. Kana: アメリカこうくううちゅうきょく, Gloss: ['Administração Nacional da Aeronáutica e Espaço (EUA)', 'NASA']"
  },
  {
    "kana": "アマダメトレックス",
    "en": [
      "Amada Metrecs Co. Ltd."
    ],
    "senseUid": "e4fbd5cc-bb6e-4c65-947c-609e9c4301b5",
    "wordId": "5010292",
    "pt": "Traduza do inglês para o português considerando o sentido japonês. Kana: アマダメトレックス, Glossário: ['Amada Metrecs Co. Ltd.']"
  },
  {
    "kana": "アモスアンドアンドリュー",
    "en": [
      "Amos & Andrew (film)"
    ],
    "senseUid": "3838431a-08a9-4881-a76f-b2cbf9d00a88",
    "wordId": "5010464",
    "pt": "Traduza do inglês para o português considerando o sentido japonês. Kana: アモスアンドアンドリュー, Gloss: ['Amos & Andrew (filme)']"
  },
  {
    "kana": "アメリカンエキスプレス",
    "en": [
      "American Express"
    ],
    "senseUid": "5dc9e440-9608-48fb-9394-831ef6830dc6",
    "wordId": "5010437",
    "pt": "Traduza do inglês para o português considerando o sentido japonês. Kana: アメリカンエキスプレス, Gloss: ['American Express']"
  },
  {
    "kana": "アラバマものがたり",
    "en": [
      "To Kill a Mockingbird (novel by Harper Lee)"
    ],
    "senseUid": "6565f669-06ff-4e92-9abb-6c57b7a42a87",
    "wordId": "5010611",
    "pt": "Traduza do inglês para o português considerando o sentido japonês. Kana: アラバマものがたり, Glossário: ['O Sol é Para Todos' (romance de Harper Lee)']"
  },
  {
    "kana": "アリアンスペース",
    "en": [
      "Arianespace"
    ],
    "senseUid": "b7611202-23a0-4453-ae64-fa653669b983",
    "wordId": "5010740",
    "pt": "Traduza do inglês para o português considerando o sentido japonês. Kana: アリアンスペース, Gloss: ['Arianespace']"
  },
  {
    "kana": "アラビアのロレンス",
    "en": [
      "Lawrence of Arabia (film)"
    ],
    "senseUid": "da80f542-345b-4dfe-a3ec-799735853dcd",
    "wordId": "5010618",
    "pt": "Traduza do inglês para o português considerando o sentido japonês. Kana: アラビアのロレンス, Glossário: ['Lawrence da Arábia (filme)']"
  },
  {
    "kana": "アリゲーターに",
    "en": [
      "Alligator 2 (film)"
    ],
    "senseUid": "655e4466-ca72-4d5f-9c4f-e185bc4ebcf9",
    "wordId": "5010770",
    "pt": "Traduza do inglês para o português considerando o sentido japonês. Kana: アリゲーターに, Gloss: ['Alligator 2 (film)']"
  },
  {
    "kana": "アリコジャパン",
    "en": [
      "Alico Japan (life insurance company)"
    ],
    "senseUid": "e92876bd-d766-4776-9148-f29bd925fd62",
    "wordId": "5010772",
    "pt": "Traduza do inglês para o português considerando o sentido japonês. Kana: アリコジャパン, Gloss: ['Alico Japan (companhia de seguro de vida)']"
  },
  {
    "kana": "アリバイのエー",
    "en": [
      "\"A\" Is for Alibi (1982 book by Sue Grafton)"
    ],
    "senseUid": "ace4f396-16ed-4158-b122-b8a77c5bf187",
    "wordId": "5010819",
    "pt": "Traduza do inglês para o português considerando o sentido japonês. Kana: アリバイのエー, Gloss: ['A Is for Alibi (livro de 1982 de Sue Grafton)']"
  },
  {
    "kana": "アリババ",
    "en": [
      "Ali Baba"
    ],
    "senseUid": "8a61a760-6eae-4a8f-99e7-8a3751eb2c9b",
    "wordId": "5010822",
    "pt": "Traduza do inglês para o português considerando o sentido japonês. Kana: アリババ, Gloss: ['Ali Baba']"
  },
  {
    "kana": "アル・ジャジーラ",
    "en": [
      "Al Jazeera"
    ],
    "senseUid": "750ba23b-5af6-4ce7-89d0-70345e12a6b2",
    "wordId": "5010861",
    "pt": "Traduza do inglês para o português considerando o sentido japonês. Kana: アル・ジャジーラ, Gloss: ['Al Jazeera']"
  },
  {
    "kana": "アルジャジーラ",
    "en": [
      "Al Jazeera"
    ],
    "senseUid": "1b78bba5-f5d2-4309-9519-ade7f8f43546",
    "wordId": "5010995",
    "pt": "Traduza do inglês para o português considerando o sentido japonês. Kana: アルジャジーラ, Gloss: ['Al Jazeera']"
  },
  {
    "kana": "アルゼンチンこうくう",
    "en": [
      "Aerolineas Argentinas (airline)"
    ],
    "senseUid": "b0ae7a18-ed59-4837-bb77-f65b3ea6dc4a",
    "wordId": "5011019",
    "pt": "Traduza do inglês para o português considerando o sentido japonês. Kana: アルゼンチンこうくう, Gloss: ['Aerolineas Argentinas (companhia)']"
  },
  {
    "kana": "アルチーナ",
    "en": [
      "Alcina (opera by Handel)"
    ],
    "senseUid": "33f58c60-f19f-48c7-b50f-b037f5bad8f1",
    "wordId": "5011058",
    "pt": "Traduza do inglês para o português considerando o sentido japonês. Kana: アルチーナ, Gloss: ['Alcina (ópera de Handel)']"
  },
  {
    "kana": "アルトバイエルン",
    "en": [
      "Altbayern (brand of sausage manufactured by Ito Ham) (lit: Old Bavaria)"
    ],
    "senseUid": "68a09329-e735-4b49-96f7-8f139a956453",
    "wordId": "5011113",
    "pt": "Traduza do inglês para o português considerando o sentido japonês. Kana: アルトバイエルン, Gloss: ['Altbayern (marca de linguiça fabricada pela Ito Ham) (lit: Baviera Antiga)']"
  },
  {
    "kana": "アルビレックスにいがた",
    "en": [
      "Albirex Niigata (professional football club)"
    ],
    "senseUid": "016dcb04-c0f7-42f0-9ca6-349f7455a77f",
    "wordId": "5011216",
    "pt": "Traduza do inglês para o português considerando o sentido japonês. Kana: アルビレックスにいがた, Glossário: ['Albirex Niigata (clube profissional de futebol)']"
  },
  {
    "kana": "アルファロメオ",
    "en": [
      "Alfa Romeo"
    ],
    "senseUid": "2fe3a27f-95b3-4fda-915b-31bc44aa5a33",
    "wordId": "5011229",
    "pt": "Traduza do inglês para o português considerando o sentido japonês. Kana: アルファロメオ, Gloss: ['Alfa Romeo']"
  },
  {
    "kana": "アレクサ",
    "en": [
      "Alexa",
      "Aleksa"
    ],
    "senseUid": "b5957038-25eb-40ce-828d-a244ce9a0580",
    "wordId": "5011467",
    "pt": "Traduza do inglês para o português considerando o sentido japonês. Kana: アレクサ, Gloss: ['Alexa', 'Aleksa']"
  },
  {
    "kana": "アレクサ",
    "en": [
      "Alexa (Amazon assistant)"
    ],
    "senseUid": "d8af9f7e-d3f3-43b9-a903-7a8f76e43f12",
    "wordId": "5011467",
    "pt": "Traduza do inglês para o português considerando o sentido japonês. Kana: アレクサ, Gloss: ['Alexa (assistente da Amazon)']"
  },
  {
    "kana": "アンタラ",
    "en": [
      "Antara (Indonesian press agency)"
    ],
    "senseUid": "91bab815-033d-441d-90f8-e53713e87c58",
    "wordId": "5011815",
    "pt": "Traduza do inglês para o português considerando o sentido japonês. Kana: アンタラ, Gloss: ['Antara (agência de imprensa indonésia)']"
  },
  {
    "kana": "アンダーザチェリームーン",
    "en": [
      "Under the Cherry Moon (film)"
    ],
    "senseUid": "82a68130-6110-4853-908e-7571b416bccb",
    "wordId": "5011822",
    "pt": "Traduza do inglês para o português considerando o sentido japonês. Kana: アンダーザチェリームーン, Gloss: ['Sob a Lua da Cereja (filme)']"
  },
  {
    "kana": "アントニーとクレオパトラ",
    "en": [
      "Antony and Cleopatra (film) (play)"
    ],
    "senseUid": "f24d8008-4e10-42c5-8294-83d318c2f910",
    "wordId": "5011916",
    "pt": "Traduza do inglês para o português considerando o sentido japonês. Kana: アントニーとクレオパトラ, Gloss: ['Antônio e Cleópatra (filme) (peça)']"
  },
  {
    "kana": "アンドロイドはでんきひつじのゆめをみるか",
    "en": [
      "Do Androids Dream of Electric Sheep? (novel by Philip K. Dick, 1968)"
    ],
    "senseUid": "ec2dd651-afa0-4e5a-8102-33b26708e92f",
    "wordId": "5012023",
    "pt": "Traduza do inglês para o português considerando o sentido japonês. Kana: アンドロイドはでんきひつじのゆめをみるか, Gloss: ['Androides sonham com ovelhas elétricas? (romance de Philip K. Dick, 1968)']"
  },
  {
    "kana": "アンドロメダのエー",
    "en": [
      "A for Andromeda (book)"
    ],
    "senseUid": "4204b590-dfbd-4a22-8c0d-23f52d3154bc",
    "wordId": "5012031",
    "pt": "Traduza do inglês para o português considerando o sentido japonês. Kana: アンドロメダのエー, Gloss: ['A de Andromeda (livro)']"
  },
  {
    "kana": "イース",
    "en": [
      "Ys (mythical city in Brittany)"
    ],
    "senseUid": "f3447b5d-0493-4804-8cc3-93c0de8e3051",
    "wordId": "5012235",
    "pt": "Traduza do inglês para o português considerando o sentido japonês. Kana: イース, Gloss: ['Ys (cidade mítica na Bretanha)']"
  },
  {
    "kana": "アンネのにっき",
    "en": [
      "The Diary of a Young Girl (journals of Anne Frank, published in 1947)"
    ],
    "senseUid": "f5ffbb25-f1dc-4df8-ba38-0937c464f599",
    "wordId": "5012053",
    "pt": "Traduza do inglês para o português considerando o sentido japonês. Kana: アンネのにっき, Gloss: ['O Diário de uma Jovem Garota (diários de Anne Frank, publicados em 1947)']"
  },
  {
    "kana": "イース",
    "en": [
      "Ys (series of games based loosely on the same legend)",
      "Eythe"
    ],
    "senseUid": "14c71435-e547-4147-a537-a232fa16c46b",
    "wordId": "5012235",
    "pt": "Traduza do inglês para o português considerando o sentido japonês. Kana: イース, Gloss: ['Ys (série de jogos vagamente baseada na mesma lenda)', 'Eythe']"
  },
  {
    "kana": "イーストエンド",
    "en": [
      "East End (London, Shanghai, etc.)"
    ],
    "senseUid": "c1136527-eeac-45a0-97cb-45749460a0b4",
    "wordId": "5012250",
    "pt": "Traduza do inglês para o português considerando o sentido japonês. Kana: イーストエンド, Gloss: ['East End (Londres, Xangai, etc.)']"
  },
  {
    "kana": "イェールだいがく",
    "en": [
      "Yale University"
    ],
    "senseUid": "115db4ea-74be-4e6a-aa9a-7ea98879c5ab",
    "wordId": "5012409",
    "pt": "Traduza do inglês para o português considerando o sentido japonês. Kana: イェールだいがく, Glossaria: ['Universidade de Yale']"
  },
  {
    "kana": "イエローサブマリン",
    "en": [
      "Yellow Submarine (film)"
    ],
    "senseUid": "f1f9aba2-483e-440f-b41a-8d0354b7195f",
    "wordId": "5012535",
    "pt": "Traduza do inglês para o português considerando o sentido japonês. Kana: イエローサブマリン, Gloss: ['Yellow Submarine (film)']"
  },
  {
    "kana": "イギリスほうそうきょうかい",
    "en": [
      "British Broadcasting Corporation",
      "BBC"
    ],
    "senseUid": "c88b0efd-e6b9-421f-af28-3c3b5349a6e8",
    "wordId": "5012611",
    "pt": "Traduza do inglês para o português considerando o sentido japonês. Kana: イギリスほうそうきょうかい, Glossário: ['British Broadcasting Corporation', 'BBC']"
  },
  {
    "kana": "イギリスれんごうおうこく",
    "en": [
      "United Kingdom of Great Britain and Northern Ireland",
      "UK"
    ],
    "senseUid": "19e7fb10-dd91-4364-95b8-d6ff5b8685d2",
    "wordId": "5012616",
    "pt": "Traduza do inglês para o português considerando o sentido japonês. Kana: イギリスれんごうおうこく, Glossário: ['Reino Unido da Grã-Bretanha e Irlanda do Norte', 'Reino Unido']"
  },
  {
    "kana": "イズベスチヤ",
    "en": [
      "Izvestia (Russian newspaper)"
    ],
    "senseUid": "6cba25a7-b27e-4e52-8657-4a3496300371",
    "wordId": "5012911",
    "pt": "Traduza do inglês para o português considerando o sentido japonês. Kana: イズベスチヤ, Gloss: ['Izvestia (jornal russo)']"
  },
  {
    "kana": "イコンとイデア",
    "en": [
      "Icon and Idea (book)"
    ],
    "senseUid": "7c508d5a-1a52-4bdc-ae60-d2ccd9eb9944",
    "wordId": "5012700",
    "pt": "Traduza do inglês para o português considerando o sentido japonês. Kana: イコンとイデア, Gloss: ['Ícone e Ideia (livro)']"
  },
  {
    "kana": "イトーヨーカドー",
    "en": [
      "Ito-Yokado"
    ],
    "senseUid": "3292a244-0a2a-4b7e-9b4d-9b6d52a9ce5c",
    "wordId": "5013126",
    "pt": "Traduza do inglês para o português considerando o sentido japonês. Kana: イトーヨーカドー, Gloss: ['Ito-Yokado']"
  },
  {
    "kana": "イスラムしょこくかいぎきこう",
    "en": [
      "Organisation of the Islamic Conference"
    ],
    "senseUid": "2c9a4819-384b-44c0-9cdd-f976d2bf461c",
    "wordId": "5012900",
    "pt": "Traduza do inglês para o português considerando o sentido japonês. Kana: イスラムしょこくかいぎきこう, Gloss: ['Organização da Conferência Islâmica']"
  },
  {
    "kana": "イトーヨーカどう",
    "en": [
      "Ito-Yokado (retail chain)"
    ],
    "senseUid": "8e204962-5af7-4a1d-accd-cf86364fe4c0",
    "wordId": "5013127",
    "pt": "Traduza do inglês para o português considerando o sentido japonês. Kana: イトーヨーカどう, Gloss: ['Ito-Yokado (rede de varejo)']"
  },
  {
    "kana": "イマジン・ジョンレノン",
    "en": [
      "Imagine - John Lennon (film)"
    ],
    "senseUid": "8fc829e4-81bb-4acf-b5a4-9b30faba08aa",
    "wordId": "5013421",
    "pt": "Traduza do inglês para o português considerando o sentido japonês. Kana: イマジン・ジョンレノン, Gloss: ['Imagine - John Lennon (filme)']"
  },
  {
    "kana": "イルミナ",
    "en": [
      "Illumina"
    ],
    "senseUid": "6fbf57f7-715d-43fd-9883-aa1af6eb9aeb",
    "wordId": "5013633",
    "pt": "Traduza do inglês para o português considerando o sentido japonês. Kana: イルミナ, Gloss: ['Illumina']"
  },
  {
    "kana": "インディアンス",
    "en": [
      "Cleveland Indians"
    ],
    "senseUid": "197c5ea0-4318-4565-94cd-803780875558",
    "wordId": "5013857",
    "pt": "Traduza do inglês para o português considerando o sentido japonês. Kana: インディアンス, Gloss: ['Cleveland Indians']"
  },
  {
    "kana": "インタビューウィズヴァンパイア",
    "en": [
      "Interview with the Vampire (film)"
    ],
    "senseUid": "f95a1565-c658-4e2f-80b5-8eff49124553",
    "wordId": "5013831",
    "pt": "Traduza do inglês para o português considerando o sentido japonês. Kana: インタビューウィズヴァンパイア, Gloss: ['Entrevista com o Vampiro (filme)']"
  },
  {
    "kana": "インドネシアこくみんとう",
    "en": [
      "Partai Nasional Indonesia"
    ],
    "senseUid": "75925d72-b19c-4074-921e-389d8740c130",
    "wordId": "5013881",
    "pt": "Traduza do inglês para o português considerando o sentido japonês. Kana: インドネシアこくみんとう, Glossaria: ['Partai Nasional Indonesia']"
  },
  {
    "kana": "インフィニオン",
    "en": [
      "Infineon"
    ],
    "senseUid": "155fe233-1d0e-44d8-bf9a-d30c6297d4bb",
    "wordId": "5013916",
    "pt": "Traduza do inglês para o português considerando o sentido japonês. Kana: インフィニオン, Gloss: ['Infineon']"
  },
  {
    "kana": "インプレッサ",
    "en": [
      "Impreza (Subaru model)"
    ],
    "senseUid": "de56ce06-e9f7-4eaa-9a56-fba636ec55d2",
    "wordId": "5013922",
    "pt": "Traduza do inglês para o português considerando o sentido japonês. Kana: インプレッサ, Gloss: ['Impreza (modelo Subaru)']"
  },
  {
    "kana": "ウーキー",
    "en": [
      "Wookiee (alien race in Star Wars)"
    ],
    "senseUid": "0ecc4323-7e43-41e3-a7eb-9caab8b707fc",
    "wordId": "5013979",
    "pt": "Traduza do inglês para o português considerando o sentido japonês. Kana: ウーキー, Gloss: ['Wookiee (raça alienígena em Star Wars)']"
  },
  {
    "kana": "ウールワース",
    "en": [
      "Woolworth Co."
    ],
    "senseUid": "c5dac096-9484-40b0-ab5e-c4931d7d21cb",
    "wordId": "5014070",
    "pt": "Traduza do inglês para o português considerando o sentido japonês. Kana: ウールワース, Gloss: ['Woolworth Co.']"
  },
  {
    "kana": "イヴサンローラン",
    "en": [
      "Yves Saint-Laurent (brand name)"
    ],
    "senseUid": "30a4bedc-0f39-4eb1-8136-6b046073f469",
    "wordId": "5013969",
    "pt": "Traduza do inglês para o português considerando o sentido japonês. Kana: イヴサンローラン, Glossário: ['Yves Saint-Laurent (nome da marca)']"
  },
  {
    "kana": "ウィー",
    "en": [
      "Wii (Nintendo video games console)"
    ],
    "senseUid": "708af373-56f7-4b85-94fe-c2053f45c4af",
    "wordId": "5014086",
    "pt": "Traduza do inglês para o português considerando o sentido japonês. Kana: ウィー, Gloss: ['Wii (console de videogame Nintendo)']"
  },
  {
    "kana": "ウィロビーチェイスのおおかみ",
    "en": [
      "The Wolves of Willoughby Chase (film)"
    ],
    "senseUid": "e8886253-06d0-48e7-a824-355446fa2034",
    "wordId": "5014574",
    "pt": "Traduza do inglês para o português considerando o sentido japonês. Kana: ウィロビーチェイスのおおかみ, Gloss: ['Os Lobos de Willoughby Chase (filme)']"
  },
  {
    "kana": "ウェーブマスター",
    "en": [
      "Wave Master (Sega studio)"
    ],
    "senseUid": "41477a9c-8f5b-4e02-a6ea-8f90e2f4dc9e",
    "wordId": "5014789",
    "pt": "Traduza do inglês para o português considerando o sentido japonês. Kana: ウェーブマスター, Gloss: ['Wave Master (Sega studio)']"
  },
  {
    "kana": "ウイングス",
    "en": [
      "Wings (British-American rock band)"
    ],
    "senseUid": "44558c90-6a2e-47ad-81ee-6dbea13ebc0d",
    "wordId": "5014737",
    "pt": "Traduza do inglês para o português considerando o sentido japonês. Kana: ウイングス, Gloss: ['Wings (banda de rock britânico-americana)']"
  },
  {
    "kana": "ウェストサイドものがたり",
    "en": [
      "Westside Story (musical by Bernstein and Sondheim)"
    ],
    "senseUid": "775a3e34-c01d-4b40-9247-f205d5b788c7",
    "wordId": "5014916",
    "pt": "Traduza do inglês para o português considerando o sentido japonês. Kana: ウェストサイドものがたり, Gloss: ['Westside Story (musical de Bernstein e Sondheim)']"
  },
  {
    "kana": "ウエストポイント",
    "en": [
      "West Point",
      "West Point Academy"
    ],
    "senseUid": "418370ce-ec97-455f-856a-7ee32e54b77e",
    "wordId": "5014953",
    "pt": "Traduza do inglês para o português considerando o sentido japonês. Kana: ウエストポイント, Gloss: ['West Point', 'Academia West Point']"
  },
  {
    "kana": "ウェブリオ",
    "en": [
      "Weblio (online dictionary)"
    ],
    "senseUid": "38d8b6d1-76c4-4a37-954c-8ad1f73f7af0",
    "wordId": "5015047",
    "pt": "Traduza do inglês para o português considerando o sentido japonês. Kana: ウェブリオ, Gloss: ['Weblio (dicionário online)']"
  },
  {
    "kana": "ウエスコ",
    "en": [
      "Wesco, Inc."
    ],
    "senseUid": "1296969e-bfcf-4ae7-aec4-9aa59312337a",
    "wordId": "5015213",
    "pt": "Traduza do inglês para o português considerando o sentido japonês. Kana: ウエスコ, Gloss: ['Wesco, Inc.']"
  },
  {
    "kana": "ウェルファイド",
    "en": [
      "Welfide Corporation"
    ],
    "senseUid": "c5362e43-21ef-49de-a118-e03297661294",
    "wordId": "5015129",
    "pt": "Traduza do inglês para o português considerando o sentido japonês. Kana: ウェルファイド, Gloss: ['Welfide Corporation']"
  },
  {
    "kana": "ウェンディーズ",
    "en": [
      "Wendy's"
    ],
    "senseUid": "0da07741-7b57-4943-9306-55d95fff1ad5",
    "wordId": "5015170",
    "pt": "Traduza do inglês para o português considerando o sentido japonês. Kana: ウェンディーズ, Gloss: [Wendy's]"
  },
  {
    "kana": "ウォークラフト",
    "en": [
      "Warcraft (computer game)"
    ],
    "senseUid": "35ace9ce-e186-4bd3-8f21-cedf1686ee6c",
    "wordId": "5015296",
    "pt": "Traduza do inglês para o português considerando o sentido japonês. Kana: ウォークラフト, Gloss: ['Warcraft (jogo de computador)']"
  },
  {
    "kana": "ながさきウエスレヤンだいがく",
    "en": [
      "Nagasaki Wesleyan University"
    ],
    "senseUid": "475423a0-08c5-4c40-a3ff-29919305e7b3",
    "wordId": "5015231",
    "pt": "Traduza do inglês para o português considerando o sentido japonês. Kana: ながさきウエスレヤンだいがく, Gloss: ['Universidade Wesleyana de Nagasaki']"
  },
  {
    "kana": "ウォールストリートジャーナル",
    "en": [
      "Wall Street Journal"
    ],
    "senseUid": "cfed8dad-b114-4161-88dd-f22f8a92ae4b",
    "wordId": "5015375",
    "pt": "Traduza do inglês para o português considerando o sentido japonês. Kana: ウォールストリートジャーナル, Gloss: ['Wall Street Journal']"
  },
  {
    "kana": "ウォレスとグルミット",
    "en": [
      "Wallace & Gromit (film series)"
    ],
    "senseUid": "4c8f6c7c-de1c-4c6f-85bb-f3d7b8a32e9d",
    "wordId": "5015589",
    "pt": "Traduza do inglês para o português considerando o sentido japonês. Kana: ウォレスとグルミット, Gloss: ['Wallace & Gromit (série de filmes)']"
  },
  {
    "kana": "ウスタシャ",
    "en": [
      "Ustaše (1929-1945; Croatian fascist organization)",
      "Ustasha",
      "Ustashe"
    ],
    "senseUid": "dfdf267b-86c6-4628-96bf-6c17b75362bf",
    "wordId": "5015727",
    "pt": "Traduza do inglês para o português considerando o sentido japonês. Kana: ウスタシャ, Gloss: ['Ustaše (1929-1945; Organização fascista croata)', 'Ustasha', 'Ustashe']"
  },
  {
    "kana": "ウルヴァリン",
    "en": [
      "Wolverine"
    ],
    "senseUid": "e9c62b1f-b3ea-4ce1-94c1-d7bb7119e93f",
    "wordId": "5016363",
    "pt": "Traduza do inglês para o português considerando o sentido japonês. Kana: ウルヴァリン, Gloss: ['Wolverine']"
  },
  {
    "kana": "ウルヴァリン",
    "en": [
      "wolverine (X-Men comic character)"
    ],
    "senseUid": "cb4baef9-3966-43c6-89db-7fb934cb08c8",
    "wordId": "5016363",
    "pt": "Traduza do inglês para o português considerando o sentido japonês. Kana: ウルヴァリン, Gloss: ['wolverine (personagem dos quadrinhos X-Men)']"
  },
  {
    "kana": "エーザイ",
    "en": [
      "Eisai (Japanese pharmaceutical company)"
    ],
    "senseUid": "1e94b7e1-a7b2-4b12-a661-22f8156e5eec",
    "wordId": "5016476",
    "pt": "Traduza do inglês para o português considerando o sentido japonês. Kana: エーザイ, Gloss: ['Eisai (empresa farmacêutica japonesa)']"
  },
  {
    "kana": "ウンマ",
    "en": [
      "Ummah",
      "Umma",
      "Muslim Ummah",
      "Islamic Ummah",
      "Islam Nation"
    ],
    "senseUid": "cb907747-03d6-4a1e-a5bb-65560171c042",
    "wordId": "5016437",
    "pt": "Traduza do inglês para o português considerando o sentido japonês. Kana: ウンマ, Gloss: ['Ummah', 'Ummah', 'Muslim Ummah', 'Islamic Ummah', 'Islam Nation']"
  },
  {
    "kana": "エーアイアイ",
    "en": [
      "AII",
      "Association of International Instructors",
      "US YMCA diving education system founded 1959"
    ],
    "senseUid": "8b384a02-0ff2-4366-88cb-4d5e688e708b",
    "wordId": "5016449",
    "pt": "Traduza do inglês para o português considerando o sentido japonês. Kana: エーアイアイ, Glossário: ['AII', 'Associação de Instrutores Internacionais', 'Sistema de educação de mergulho YMCA dos EUA fundado em 1959']"
  },
  {
    "kana": "エールだいがく",
    "en": [
      "Yale University"
    ],
    "senseUid": "954f947e-e307-4af6-b992-081bff7ea5c0",
    "wordId": "5016581",
    "pt": "Traduza do inglês para o português considerando o sentido japonês. Kana: エールだいがく, Gloss: ['Universidade de Yale']"
  },
  {
    "kana": "エア・タヒチ",
    "en": [
      "Air Tahiti"
    ],
    "senseUid": "a89f4549-c420-4b2b-9843-0b273a340e04",
    "wordId": "5016608",
    "pt": "Traduza do inglês para o português considerando o sentido japonês. Kana: エア・タヒチ, Gloss: ['Air Tahiti']"
  },
  {
    "kana": "エア・タヒチ・ヌイ",
    "en": [
      "Air Tahiti Nui"
    ],
    "senseUid": "32e74797-75ab-47ae-be52-0b37b86daa6a",
    "wordId": "5016609",
    "pt": "Traduza do inglês para o português considerando o sentido japonês. Kana: エア・タヒチ・ヌイ, Gloss: ['Air Tahiti Nui']"
  },
  {
    "kana": "エアーニッポン",
    "en": [
      "Air Nippon"
    ],
    "senseUid": "a8e39b1f-0cd5-4a9c-a232-e72883cfd296",
    "wordId": "5016614",
    "pt": "Traduza do inglês para o português considerando o sentido japonês. Kana: エアーニッポン, Gloss: ['Air Nippon']"
  },
  {
    "kana": "エアウルフ",
    "en": [
      "Mission Airwolf (film)"
    ],
    "senseUid": "9f656395-9bf4-49f9-91a3-6bb0a291ad48",
    "wordId": "5016616",
    "pt": "Traduza do inglês para o português considerando o sentido japonês. Kana: エアウルフ, Gloss: ['Missão Lobo Aéreo (filme)']"
  },
  {
    "kana": "エアタヒチ",
    "en": [
      "Air Tahiti"
    ],
    "senseUid": "687b6023-d3e6-4edb-8b2b-f26188e124ed",
    "wordId": "5016619",
    "pt": "Traduza do inglês para o português considerando o sentido japonês. Kana: エアタヒチ, Gloss: ['Air Tahiti']"
  },
  {
    "kana": "エアバス",
    "en": [
      "Airbus"
    ],
    "senseUid": "d087f8c1-bcd5-43aa-8cf1-5bea57cc3628",
    "wordId": "5016626",
    "pt": "Traduza do inglês para o português considerando o sentido japonês. Kana: エアバス, Gloss: ['Airbus']"
  },
  {
    "kana": "エアタヒチヌイ",
    "en": [
      "Air Tahiti Nui"
    ],
    "senseUid": "800cab17-2503-499a-8e22-9ce5c95884d2",
    "wordId": "5016620",
    "pt": "Traduza do inglês para o português considerando o sentido japonês. Kana: エアタヒチヌイ, Gloss: ['Air Tahiti Nui']"
  },
  {
    "kana": "エアリンガス",
    "en": [
      "Aer Lingus"
    ],
    "senseUid": "5c32e1b0-3efe-4e57-a845-3333cc7a7112",
    "wordId": "5016633",
    "pt": "Traduza do inglês para o português considerando o sentido japonês. Kana: エアリンガス, Gloss: ['Aer Lingus']"
  },
  {
    "kana": "エイサー",
    "en": [
      "Acer"
    ],
    "senseUid": "f0f56537-d25d-44da-8cb8-c44789e11410",
    "wordId": "5016662",
    "pt": "Traduza do inglês para o português considerando o sentido japonês. Kana: エイサー, Gloss: ['Acer']"
  },
  {
    "kana": "エイベックス",
    "en": [
      "Avex Entertainment Inc.",
      "Avex"
    ],
    "senseUid": "ee25432e-c8b9-4124-8524-43a349d9df8c",
    "wordId": "5016718",
    "pt": "Traduza do inglês para o português considerando o sentido japonês. Kana: エイベックス, Glossaria: ['Avex Entertainment Inc.', 'Avex']"
  },
  {
    "kana": "エイプマンひとりぼっち",
    "en": [
      "Missing Link (film)"
    ],
    "senseUid": "ba5e1c25-b5ba-4ab3-bc89-ab2e4269724a",
    "wordId": "5016716",
    "pt": "Traduza do inglês para o português considerando o sentido japonês. Kana: エイプマンひとりぼっち, Glossaria: ['Missing Link (filme)']"
  },
  {
    "kana": "エクソシスト",
    "en": [
      "The Exorcist (film)"
    ],
    "senseUid": "2e84ac1c-dff3-47fc-b661-64415110d096",
    "wordId": "5016863",
    "pt": "Traduza do inglês para o português considerando o sentido japonês. Kana: エクソシスト, Glossário: ['O Exorcista (filme)']"
  },
  {
    "kana": "エイリアンブイエスプレデター",
    "en": [
      "Alien vs. Predator (film)"
    ],
    "senseUid": "7a313958-46c8-4c59-a18f-0f37de369591",
    "wordId": "5016742",
    "pt": "Traduza do inglês para o português considerando o sentido japonês. Kana: エイリアンブイエスプレデター, Gloss: ['Alien vs. Predator (filme)']"
  },
  {
    "kana": "エクソン・モービル",
    "en": [
      "Exxon Mobil"
    ],
    "senseUid": "5ba5407e-b2e5-41f4-8b21-31158f636cad",
    "wordId": "5016865",
    "pt": "Traduza do inglês para o português considerando o sentido japonês. Kana: エクソン・モービル, Gloss: ['Exxon Mobil']"
  },
  {
    "kana": "エグゼクティブデシジョン",
    "en": [
      "Executive Decision (film)"
    ],
    "senseUid": "ed0e3161-4200-4ba9-bcd1-471f0bba3dfa",
    "wordId": "5016897",
    "pt": "Traduza do inglês para o português considerando o sentido japonês. Kana: エグゼクティブデシジョン, Gloss: ['Decisão Executiva (filme)']"
  },
  {
    "kana": "エクソンモービル",
    "en": [
      "Exxon Mobil"
    ],
    "senseUid": "1044aac5-da07-4084-8fe1-0537dde52220",
    "wordId": "5016866",
    "pt": "Traduza do inglês para o português considerando o sentido japonês. Kana: エクソンモービル, Gloss: ['Exxon Mobil']"
  },
  {
    "kana": "エス・エヌ・ケイ",
    "en": [
      "SNK"
    ],
    "senseUid": "ba14e8f7-4cc1-4c15-996e-5894a49b4146",
    "wordId": "5016996",
    "pt": "Traduza do inglês para o português considerando o sentido japonês. Kana: エス・エヌ・ケイ, Gloss: ['SNK']"
  },
  {
    "kana": "エグゼクティブ・デシジョン",
    "en": [
      "Executive Decision (film)"
    ],
    "senseUid": "0039eed6-355b-4870-a7c1-8171346a8dd9",
    "wordId": "5016896",
    "pt": "Traduza do inglês para o português considerando o sentido japonês. Kana: エグゼクティブ・デシジョン, Glossário: ['Decisão Executiva (filme)']"
  },
  {
    "kana": "エジプトこうくう",
    "en": [
      "EgyptAir"
    ],
    "senseUid": "f93c8785-da5f-460c-ac5a-9d4029e7a337",
    "wordId": "5016986",
    "pt": "Traduza do inglês para o português considerando o sentido japonês. Kana: エジプトこうくう, Gloss: ['EgyptAir']"
  },
  {
    "kana": "エスエヌケイ",
    "en": [
      "SNK"
    ],
    "senseUid": "7aff5068-ecb4-4a02-bfc5-eecb28361a67",
    "wordId": "5017000",
    "pt": "Traduza do inglês para o português considerando o sentido japonês. Kana: エスエヌケイ, Gloss: ['SNK']"
  },
  {
    "kana": "エスエスアイ",
    "en": [
      "SSI",
      "Scuba Schools International"
    ],
    "senseUid": "e87d70d0-f25c-494a-bd26-4e73431d965a",
    "wordId": "5016999",
    "pt": "Traduza do inglês para o português considerando o sentido japonês. Kana: エスエスアイ, Glossário: ['SSI', 'Escolas de Mergulho Internacional']"
  },
  {
    "kana": "エスモード",
    "en": [
      "Esmod (fashion course trainer)"
    ],
    "senseUid": "871c821c-8764-4bd1-b867-9fa6244ac363",
    "wordId": "5017154",
    "pt": "Traduza do inglês para o português considerando o sentido japonês. Kana: エスモード, Gloss: ['Esmod (treinador de curso de moda)']"
  },
  {
    "kana": "エチオピアこうくう",
    "en": [
      "Ethiopian Airlines"
    ],
    "senseUid": "635da9f0-5dbc-4bb1-b345-84d6af8f3fd9",
    "wordId": "5017209",
    "pt": "Traduza do inglês para o português considerando o sentido japonês. Kana: エチオピアこうくう, Gloss: ['Ethiopian Airlines']"
  },
  {
    "kana": "エツェル",
    "en": [
      "Etzel",
      "Irgun"
    ],
    "senseUid": "664abbf5-bfc4-4864-8459-1a6266c509d7",
    "wordId": "5017316",
    "pt": "Traduza do inglês para o português considerando o sentido japonês. Kana: エツェル, Gloss: ['Etzel', 'Irgun']"
  },
  {
    "kana": "エニックス",
    "en": [
      "Enix (now Square Enix)"
    ],
    "senseUid": "a720d683-635c-4f70-800f-f95cc113cc3e",
    "wordId": "5017521",
    "pt": "Traduza do inglês para o português considerando o sentido japonês. Kana: エニックス, Gloss: ['Enix (agora Square Enix)']"
  },
  {
    "kana": "エプソン",
    "en": [
      "Epson"
    ],
    "senseUid": "77c928e9-838c-4582-bb07-c65fd70f1044",
    "wordId": "5017711",
    "pt": "Traduza do inglês para o português considerando o sentido japonês. Kana: エプソン, Gloss: ['Epson']"
  },
  {
    "kana": "エルパイス",
    "en": [
      "El Pais (Spanish newspaper)"
    ],
    "senseUid": "8235faca-da00-4df7-a758-8641e47a88ff",
    "wordId": "5018225",
    "pt": "Traduza do inglês para o português considerando o sentido japonês. Kana: エルパイス, Gloss: ['El País (jornal espanhol)']"
  },
  {
    "kana": "エディアンドザクルーザーズ",
    "en": [
      "Eddie And the Cruisers (film)"
    ],
    "senseUid": "5e329785-be56-4431-a455-942645b6bece",
    "wordId": "5017339",
    "pt": "Traduza do inglês para o português considerando o sentido japonês. Kana: エディアンドザクルーザーズ, Gloss: ['Eddie e os Cruzadores (filme)']"
  },
  {
    "kana": "エルメス",
    "en": [
      "Hermès (luxury goods brand)"
    ],
    "senseUid": "e947aab4-82ac-495e-97d9-ab54a4217d33",
    "wordId": "5018316",
    "pt": "Traduza do inglês para o português considerando o sentido japonês. Kana: エルメス, Gloss: ['Hermès (marca de artigos de luxo)']"
  }
]